django_pgrls/__init__.py
django_pgrls/apps.py
django_pgrls/checks.py
django_pgrls/constraints.py
django_pgrls/contrib/__init__.py
django_pgrls/contrib/cache.py
django_pgrls/contrib/storage.py
django_pgrls/log.py
django_pgrls/models.py
django_pgrls/postgresql/__init__.py
django_pgrls/postgresql/base.py
django_pgrls/postgresql/schema.py
django_pgrls/py.typed
django_pgrls/queries.py
django_pgrls/routing/__init__.py
django_pgrls/routing/info.py
django_pgrls/routing/middleware.py
django_pgrls/routing/models.py
django_pgrls/routing/urlresolvers.py
django_pgrls/settings.py
django_pgrls/state.py
django_pgrls/utils.py
django_pgrls-0.2.4.dist-info/LICENSE
django_pgrls-0.2.4.dist-info/METADATA
django_pgrls-0.2.4.dist-info/WHEEL
django_pgrls-0.2.4.dist-info/RECORD
