Metadata-Version: 2.1
Name: django-pgrls
Version: 0.2.4
Summary: Django multi-tenancy through Postgres row level security
Home-page: https://github.com/lorinkoz/django-pgrls
License: MIT
Keywords: django,postgres,multi-tenancy,row-level-security
Author: Lorenzo Peña
Author-email: lorinkoz@gmail.com
Requires-Python: >=3.10,<4.0
Classifier: Development Status :: 3 - Alpha
Classifier: Framework :: Django
Classifier: Framework :: Django :: 4.2
Classifier: Framework :: Django :: 5.0
Classifier: License :: OSI Approved :: MIT License
Classifier: Programming Language :: Python :: 3
Classifier: Programming Language :: Python :: 3.10
Classifier: Programming Language :: Python :: 3.11
Classifier: Programming Language :: Python :: 3.12
Requires-Dist: django (>=4.2)
Project-URL: Documentation, https://django-pgrls.readthedocs.io/
Project-URL: Repository, https://github.com/lorinkoz/django-pgrls
